[ {
  "@id" : "_:genid1",
  "@type" : [ "http://www.w3.org/2006/vcard/ns#Individual" ],
  "http://www.w3.org/2006/vcard/ns#family-name" : [ {
    "@value" : "Bonduel"
  } ],
  "http://www.w3.org/2006/vcard/ns#fn" : [ {
    "@value" : "Mathias Bonduel"
  } ],
  "http://www.w3.org/2006/vcard/ns#given-name" : [ {
    "@value" : "Mathias"
  } ],
  "http://www.w3.org/2006/vcard/ns#hasOrganizationName" : [ {
    "@id" : "_:genid2"
  } ],
  "http://www.w3.org/2006/vcard/ns#hasURL" : [ {
    "@id" : "https://orcid.org/0000-0002-3313-924X"
  }, {
    "@id" : "https://www.kuleuven.be/wieiswie/nl/person/00110827"
  }, {
    "@id" : "https://www.researchgate.net/profile/Mathias_Bonduel"
  } ]
}, {
  "@id" : "_:genid2",
  "@type" : [ "http://www.w3.org/2006/vcard/ns#Organization" ],
  "http://www.w3.org/2006/vcard/ns#hasURL" : [ {
    "@id" : "https://www.kuleuven.be"
  } ],
  "http://www.w3.org/2006/vcard/ns#organization-name" : [ {
    "@value" : "KU Leuven"
  } ]
}, {
  "@id" : "http://creativecommons.org/ns#license",
  "@type" : [ "http://www.w3.org/2002/07/owl#AnnotationProperty" ]
}, {
  "@id" : "http://pi.pauwel.be/voc/buildingelement#Slab-ROOF",
  "@type" : [ "http://www.w3.org/2002/07/owl#NamedIndividual", "http://www.w3.org/2000/01/rdf-schema#Resource" ]
}, {
  "@id" : "http://purl.org/dc/terms/creator",
  "@type" : [ "http://www.w3.org/2002/07/owl#AnnotationProperty" ]
}, {
  "@id" : "http://purl.org/dc/terms/description",
  "@type" : [ "http://www.w3.org/2002/07/owl#AnnotationProperty" ]
}, {
  "@id" : "http://purl.org/dc/terms/issued",
  "@type" : [ "http://www.w3.org/2002/07/owl#AnnotationProperty" ]
}, {
  "@id" : "http://purl.org/dc/terms/source",
  "@type" : [ "http://www.w3.org/2002/07/owl#AnnotationProperty" ]
}, {
  "@id" : "http://purl.org/dc/terms/title",
  "@type" : [ "http://www.w3.org/2002/07/owl#AnnotationProperty" ]
}, {
  "@id" : "http://purl.org/vocab/vann/preferredNamespacePrefix",
  "@type" : [ "http://www.w3.org/2002/07/owl#AnnotationProperty" ]
}, {
  "@id" : "http://purl.org/vocab/vann/preferredNamespaceUri",
  "@type" : [ "http://www.w3.org/2002/07/owl#AnnotationProperty" ]
}, {
  "@id" : "http://purl.org/vocommons/voaf#Vocabulary",
  "@type" : [ "http://www.w3.org/2002/07/owl#Class" ]
}, {
  "@id" : "http://www.w3.org/2000/01/rdf-schema#Resource",
  "@type" : [ "http://www.w3.org/2002/07/owl#Class" ]
}, {
  "@id" : "http://www.w3.org/2004/02/skos/core#Concept",
  "@type" : [ "http://www.w3.org/2002/07/owl#Class" ]
}, {
  "@id" : "http://www.w3.org/2006/vcard/ns#Individual",
  "@type" : [ "http://www.w3.org/2002/07/owl#Class", "http://www.w3.org/2002/07/owl#NamedIndividual", "http://www.w3.org/2000/01/rdf-schema#Resource" ]
}, {
  "@id" : "http://www.w3.org/2006/vcard/ns#Organization",
  "@type" : [ "http://www.w3.org/2002/07/owl#Class", "http://www.w3.org/2002/07/owl#NamedIndividual", "http://www.w3.org/2000/01/rdf-schema#Resource" ]
}, {
  "@id" : "http://www.w3.org/2006/vcard/ns#family-name",
  "@type" : [ "http://www.w3.org/2002/07/owl#AnnotationProperty" ]
}, {
  "@id" : "http://www.w3.org/2006/vcard/ns#fn",
  "@type" : [ "http://www.w3.org/2002/07/owl#AnnotationProperty" ]
}, {
  "@id" : "http://www.w3.org/2006/vcard/ns#given-name",
  "@type" : [ "http://www.w3.org/2002/07/owl#AnnotationProperty" ]
}, {
  "@id" : "http://www.w3.org/2006/vcard/ns#hasOrganizationName",
  "@type" : [ "http://www.w3.org/2002/07/owl#AnnotationProperty" ]
}, {
  "@id" : "http://www.w3.org/2006/vcard/ns#hasURL",
  "@type" : [ "http://www.w3.org/2002/07/owl#AnnotationProperty" ]
}, {
  "@id" : "http://www.w3.org/2006/vcard/ns#organization-name",
  "@type" : [ "http://www.w3.org/2002/07/owl#AnnotationProperty" ]
}, {
  "@id" : "https://id.erfgoed.net/thesauri/aanduidingstypes",
  "@type" : [ "http://www.w3.org/2002/07/owl#NamedIndividual", "http://www.w3.org/2000/01/rdf-schema#Resource" ]
}, {
  "@id" : "https://id.erfgoed.net/thesauri/dateringen/1195",
  "@type" : [ "http://www.w3.org/2002/07/owl#NamedIndividual", "http://www.w3.org/2000/01/rdf-schema#Resource" ]
}, {
  "@id" : "https://id.erfgoed.net/thesauri/dateringen/1196",
  "@type" : [ "http://www.w3.org/2002/07/owl#NamedIndividual", "http://www.w3.org/2000/01/rdf-schema#Resource" ]
}, {
  "@id" : "https://id.erfgoed.net/thesauri/dateringen/1223",
  "@type" : [ "http://www.w3.org/2002/07/owl#NamedIndividual", "http://www.w3.org/2000/01/rdf-schema#Resource" ]
}, {
  "@id" : "https://id.erfgoed.net/thesauri/dateringen/1227",
  "@type" : [ "http://www.w3.org/2002/07/owl#NamedIndividual", "http://www.w3.org/2000/01/rdf-schema#Resource" ]
}, {
  "@id" : "https://id.erfgoed.net/thesauri/dateringen/1236",
  "@type" : [ "http://www.w3.org/2002/07/owl#NamedIndividual", "http://www.w3.org/2000/01/rdf-schema#Resource" ]
}, {
  "@id" : "https://id.erfgoed.net/thesauri/dateringen/1237",
  "@type" : [ "http://www.w3.org/2002/07/owl#NamedIndividual", "http://www.w3.org/2000/01/rdf-schema#Resource" ]
}, {
  "@id" : "https://id.erfgoed.net/thesauri/waardetypes",
  "@type" : [ "http://www.w3.org/2002/07/owl#NamedIndividual", "http://www.w3.org/2000/01/rdf-schema#Resource" ]
}, {
  "@id" : "https://id.erfgoed.net/thesauri/waardetypes/30",
  "@type" : [ "http://www.w3.org/2002/07/owl#NamedIndividual", "http://www.w3.org/2004/02/skos/core#Concept" ]
}, {
  "@id" : "https://id.erfgoed.net/thesauri/waardetypes/37",
  "@type" : [ "http://www.w3.org/2002/07/owl#NamedIndividual", "http://www.w3.org/2004/02/skos/core#Concept" ]
}, {
  "@id" : "https://inventaris.onroerenderfgoed.be/",
  "@type" : [ "http://www.w3.org/2002/07/owl#NamedIndividual", "http://www.w3.org/2000/01/rdf-schema#Resource" ]
}, {
  "@id" : "https://w3id.org/bot#Building",
  "@type" : [ "http://www.w3.org/2002/07/owl#Class" ]
}, {
  "@id" : "https://w3id.org/bot#Element",
  "@type" : [ "http://www.w3.org/2002/07/owl#Class" ]
}, {
  "@id" : "https://w3id.org/bot#Interface",
  "@type" : [ "http://www.w3.org/2002/07/owl#Class" ]
}, {
  "@id" : "https://w3id.org/bot#Site",
  "@type" : [ "http://www.w3.org/2002/07/owl#Class" ]
}, {
  "@id" : "https://w3id.org/bot#Zone",
  "@type" : [ "http://www.w3.org/2002/07/owl#Class" ]
}, {
  "@id" : "https://w3id.org/con-tax#Architect",
  "@type" : [ "http://www.w3.org/2002/07/owl#Class" ]
}, {
  "@id" : "https://w3id.org/con-tax#ConstructionComponent",
  "@type" : [ "http://www.w3.org/2002/07/owl#Class" ]
}, {
  "@id" : "https://w3id.org/con-tax#Material",
  "@type" : [ "http://www.w3.org/2002/07/owl#Class" ]
}, {
  "@id" : "https://w3id.org/con-tax#domainOrSubjectIncludes",
  "@type" : [ "http://www.w3.org/2002/07/owl#AnnotationProperty" ]
}, {
  "@id" : "https://w3id.org/con-tax#property_DP",
  "@type" : [ "http://www.w3.org/2002/07/owl#DatatypeProperty" ]
}, {
  "@id" : "https://w3id.org/con-tax#property_OP",
  "@type" : [ "http://www.w3.org/2002/07/owl#ObjectProperty" ]
}, {
  "@id" : "https://w3id.org/con-tax#rangeOrObjectIncludes",
  "@type" : [ "http://www.w3.org/2002/07/owl#AnnotationProperty" ]
}, {
  "@id" : "https://w3id.org/con-tax/components/aat-arch#300002098",
  "@type" : [ "http://www.w3.org/2002/07/owl#NamedIndividual", "http://www.w3.org/2000/01/rdf-schema#Resource" ]
}, {
  "@id" : "https://w3id.org/con-tax/properties/bhp",
  "@type" : [ "http://www.w3.org/2002/07/owl#Ontology", "http://www.w3.org/2002/07/owl#NamedIndividual", "http://purl.org/vocommons/voaf#Vocabulary" ],
  "http://creativecommons.org/ns#license" : [ {
    "@id" : "https://creativecommons.org/licenses/by/4.0/"
  } ],
  "http://purl.org/dc/terms/creator" : [ {
    "@id" : "_:genid1"
  } ],
  "http://purl.org/dc/terms/description" : [ {
    "@language" : "en",
    "@value" : "This ontology contains a preliminary list of properties that might prove useful to describe heritage buildings. Besides two taxonomies of general built heritage properties, extending resp. contax:property_OP and contax:property_DP, it also contains terminology for the more specific patterns related to construction assessments (extending the more generic Construction Properties (CP) taxonomy). The properties are inspired by (1) the databases of Monumentenwacht Vlaanderen (MAKSBO and IMACS), (2) the online built heritage inventory of Onroerend Erfgoed Vlaanderen and (3) the results of interviews with a large variety of Flemish built heritage stakeholders."
  } ],
  "http://purl.org/dc/terms/issued" : [ {
    "@type" : "http://www.w3.org/2001/XMLSchema#date",
    "@value" : "2020-12-19"
  } ],
  "http://purl.org/dc/terms/title" : [ {
    "@language" : "en",
    "@value" : "Built Heritage Properties (BHP) taxonomy"
  } ],
  "http://purl.org/vocab/vann/preferredNamespacePrefix" : [ {
    "@value" : "bhp"
  } ],
  "http://purl.org/vocab/vann/preferredNamespaceUri" : [ {
    "@value" : "https://w3id.org/con-tax/properties/bhp#"
  } ],
  "http://www.w3.org/2000/01/rdf-schema#comment" : [ {
    "@language" : "en",
    "@value" : "- Version 0.0.1: initial version"
  } ],
  "http://www.w3.org/2002/07/owl#versionInfo" : [ {
    "@value" : "0.0.1"
  } ]
}, {
  "@id" : "https://w3id.org/con-tax/properties/bhp#buildingFunction",
  "@type" : [ "http://www.w3.org/2002/07/owl#ObjectProperty" ],
  "http://purl.org/dc/terms/source" : [ {
    "@id" : "https://www.monumentenwacht.be/"
  } ],
  "http://www.w3.org/2000/01/rdf-schema#comment" : [ {
    "@language" : "en",
    "@value" : "Property to assign a function to a certain built heritage building. For the Flemish context, predefined property values can be used from ET-BUILDINGS taxonomy, based on the Onroerend Erfgoed thesaurus \"ERFGOEDTYPES\", and the AAT-BUILDINGS taxonomy based on the Getty AAT. Property definition inspired by the Monumentenwacht Vlaanderen databases (MAKSBO and IMACS)."
  } ],
  "http://www.w3.org/2000/01/rdf-schema#isDefinedBy" : [ {
    "@id" : "https://w3id.org/con-tax/properties/bhp"
  } ],
  "http://www.w3.org/2000/01/rdf-schema#label" : [ {
    "@language" : "en",
    "@value" : "building function"
  } ],
  "http://www.w3.org/2000/01/rdf-schema#subPropertyOf" : [ {
    "@id" : "https://w3id.org/con-tax#property_OP"
  } ],
  "https://w3id.org/con-tax#domainOrSubjectIncludes" : [ {
    "@id" : "https://w3id.org/bot#Building"
  } ],
  "https://w3id.org/con-tax#rangeOrObjectIncludes" : [ {
    "@id" : "https://w3id.org/con-tax/zones/aat-buildings#300004790"
  }, {
    "@id" : "https://w3id.org/con-tax/zones/et-buildings#1226"
  }, {
    "@id" : "https://w3id.org/con-tax/zones/et-buildings#1271"
  }, {
    "@id" : "https://w3id.org/con-tax/zones/et-buildings#293"
  }, {
    "@id" : "https://w3id.org/con-tax/zones/et-buildings#319"
  }, {
    "@id" : "https://w3id.org/con-tax/zones/et-buildings#321"
  }, {
    "@id" : "https://w3id.org/con-tax/zones/et-buildings#323"
  }, {
    "@id" : "https://w3id.org/con-tax/zones/et-buildings#359"
  }, {
    "@id" : "https://w3id.org/con-tax/zones/et-buildings#466"
  }, {
    "@id" : "https://w3id.org/con-tax/zones/et-buildings#520"
  }, {
    "@id" : "https://w3id.org/con-tax/zones/et-buildings#63"
  } ]
}, {
  "@id" : "https://w3id.org/con-tax/properties/bhp#buildingFunction_current",
  "@type" : [ "http://www.w3.org/2002/07/owl#ObjectProperty" ],
  "http://purl.org/dc/terms/source" : [ {
    "@id" : "https://www.monumentenwacht.be/"
  } ],
  "http://www.w3.org/2000/01/rdf-schema#comment" : [ {
    "@language" : "en",
    "@value" : "Property to assign a current function to a certain built heritage building. An alternative way of modeling the current function of a building is by attaching the appropriate class (specialization of bot:Building) to the building node via an rdf:type relation. For the Flemish context, predefined property values can be used from ET-BUILDINGS taxonomy, based on the Onroerend Erfgoed thesaurus \"ERFGOEDTYPES\", and the AAT-BUILDINGS taxonomy based on the Getty AAT. Property definition inspired by the Monumentenwacht Vlaanderen databases (MAKSBO and IMACS)."
  } ],
  "http://www.w3.org/2000/01/rdf-schema#isDefinedBy" : [ {
    "@id" : "https://w3id.org/con-tax/properties/bhp"
  } ],
  "http://www.w3.org/2000/01/rdf-schema#label" : [ {
    "@language" : "en",
    "@value" : "current building function"
  } ],
  "http://www.w3.org/2000/01/rdf-schema#subPropertyOf" : [ {
    "@id" : "https://w3id.org/con-tax/properties/bhp#buildingFunction"
  } ],
  "https://w3id.org/con-tax#domainOrSubjectIncludes" : [ {
    "@id" : "https://w3id.org/bot#Building"
  } ],
  "https://w3id.org/con-tax#rangeOrObjectIncludes" : [ {
    "@id" : "https://w3id.org/con-tax/zones/aat-buildings#300004790"
  }, {
    "@id" : "https://w3id.org/con-tax/zones/et-buildings#1226"
  }, {
    "@id" : "https://w3id.org/con-tax/zones/et-buildings#1271"
  }, {
    "@id" : "https://w3id.org/con-tax/zones/et-buildings#293"
  }, {
    "@id" : "https://w3id.org/con-tax/zones/et-buildings#319"
  }, {
    "@id" : "https://w3id.org/con-tax/zones/et-buildings#321"
  }, {
    "@id" : "https://w3id.org/con-tax/zones/et-buildings#323"
  }, {
    "@id" : "https://w3id.org/con-tax/zones/et-buildings#359"
  }, {
    "@id" : "https://w3id.org/con-tax/zones/et-buildings#466"
  }, {
    "@id" : "https://w3id.org/con-tax/zones/et-buildings#520"
  }, {
    "@id" : "https://w3id.org/con-tax/zones/et-buildings#63"
  } ]
}, {
  "@id" : "https://w3id.org/con-tax/properties/bhp#buildingFunction_original",
  "@type" : [ "http://www.w3.org/2002/07/owl#ObjectProperty" ],
  "http://purl.org/dc/terms/source" : [ {
    "@id" : "https://www.monumentenwacht.be/"
  } ],
  "http://www.w3.org/2000/01/rdf-schema#comment" : [ {
    "@language" : "en",
    "@value" : "Property to assign an original function to a certain built heritage building. For the Flemish context, predefined property values can be used from ET-BUILDINGS taxonomy, based on the Onroerend Erfgoed thesaurus \"ERFGOEDTYPES\", and the AAT-BUILDINGS taxonomy based on the Getty AAT. Property definition inspired by the Monumentenwacht Vlaanderen databases (MAKSBO and IMACS)."
  } ],
  "http://www.w3.org/2000/01/rdf-schema#isDefinedBy" : [ {
    "@id" : "https://w3id.org/con-tax/properties/bhp"
  } ],
  "http://www.w3.org/2000/01/rdf-schema#label" : [ {
    "@language" : "en",
    "@value" : "original building function"
  } ],
  "http://www.w3.org/2000/01/rdf-schema#subPropertyOf" : [ {
    "@id" : "https://w3id.org/con-tax/properties/bhp#buildingFunction"
  } ],
  "https://w3id.org/con-tax#domainOrSubjectIncludes" : [ {
    "@id" : "https://w3id.org/bot#Building"
  } ],
  "https://w3id.org/con-tax#rangeOrObjectIncludes" : [ {
    "@id" : "https://w3id.org/con-tax/zones/aat-buildings#300004790"
  }, {
    "@id" : "https://w3id.org/con-tax/zones/et-buildings#1226"
  }, {
    "@id" : "https://w3id.org/con-tax/zones/et-buildings#1271"
  }, {
    "@id" : "https://w3id.org/con-tax/zones/et-buildings#293"
  }, {
    "@id" : "https://w3id.org/con-tax/zones/et-buildings#319"
  }, {
    "@id" : "https://w3id.org/con-tax/zones/et-buildings#321"
  }, {
    "@id" : "https://w3id.org/con-tax/zones/et-buildings#323"
  }, {
    "@id" : "https://w3id.org/con-tax/zones/et-buildings#359"
  }, {
    "@id" : "https://w3id.org/con-tax/zones/et-buildings#466"
  }, {
    "@id" : "https://w3id.org/con-tax/zones/et-buildings#520"
  }, {
    "@id" : "https://w3id.org/con-tax/zones/et-buildings#63"
  } ]
}, {
  "@id" : "https://w3id.org/con-tax/properties/bhp#buildingFunction_past",
  "@type" : [ "http://www.w3.org/2002/07/owl#ObjectProperty" ],
  "http://purl.org/dc/terms/source" : [ {
    "@id" : "https://www.monumentenwacht.be/"
  } ],
  "http://www.w3.org/2000/01/rdf-schema#comment" : [ {
    "@language" : "en",
    "@value" : "Property to assign a past function (different from the original function) to a certain built heritage building. For the Flemish context, predefined property values can be used from ET-BUILDINGS taxonomy, based on the Onroerend Erfgoed thesaurus \"ERFGOEDTYPES\", and the AAT-BUILDINGS taxonomy based on the Getty AAT. Property definition inspired by the Monumentenwacht Vlaanderen databases (MAKSBO and IMACS)."
  } ],
  "http://www.w3.org/2000/01/rdf-schema#isDefinedBy" : [ {
    "@id" : "https://w3id.org/con-tax/properties/bhp"
  } ],
  "http://www.w3.org/2000/01/rdf-schema#label" : [ {
    "@language" : "en",
    "@value" : "past building function"
  } ],
  "http://www.w3.org/2000/01/rdf-schema#subPropertyOf" : [ {
    "@id" : "https://w3id.org/con-tax/properties/bhp#buildingFunction"
  } ],
  "https://w3id.org/con-tax#domainOrSubjectIncludes" : [ {
    "@id" : "https://w3id.org/bot#Building"
  } ],
  "https://w3id.org/con-tax#rangeOrObjectIncludes" : [ {
    "@id" : "https://w3id.org/con-tax/zones/aat-buildings#300004790"
  }, {
    "@id" : "https://w3id.org/con-tax/zones/et-buildings#1226"
  }, {
    "@id" : "https://w3id.org/con-tax/zones/et-buildings#1271"
  }, {
    "@id" : "https://w3id.org/con-tax/zones/et-buildings#293"
  }, {
    "@id" : "https://w3id.org/con-tax/zones/et-buildings#319"
  }, {
    "@id" : "https://w3id.org/con-tax/zones/et-buildings#321"
  }, {
    "@id" : "https://w3id.org/con-tax/zones/et-buildings#323"
  }, {
    "@id" : "https://w3id.org/con-tax/zones/et-buildings#359"
  }, {
    "@id" : "https://w3id.org/con-tax/zones/et-buildings#466"
  }, {
    "@id" : "https://w3id.org/con-tax/zones/et-buildings#520"
  }, {
    "@id" : "https://w3id.org/con-tax/zones/et-buildings#63"
  } ]
}, {
  "@id" : "https://w3id.org/con-tax/properties/bhp#describedByHistoricalSource",
  "@type" : [ "http://www.w3.org/2002/07/owl#ObjectProperty" ],
  "http://www.w3.org/2000/01/rdf-schema#comment" : [ {
    "@language" : "en",
    "@value" : "A property to connect a spatial building zone or construction component to a historical source that describes it. Property definition inspired by interviews with built heritage stakeholders."
  } ],
  "http://www.w3.org/2000/01/rdf-schema#isDefinedBy" : [ {
    "@id" : "https://w3id.org/con-tax/properties/bhp"
  } ],
  "http://www.w3.org/2000/01/rdf-schema#label" : [ {
    "@language" : "en",
    "@value" : "described by historical source"
  } ],
  "http://www.w3.org/2000/01/rdf-schema#subPropertyOf" : [ {
    "@id" : "https://w3id.org/con-tax#property_OP"
  } ],
  "https://w3id.org/con-tax#domainOrSubjectIncludes" : [ {
    "@id" : "https://w3id.org/bot#Element"
  }, {
    "@id" : "https://w3id.org/bot#Zone"
  }, {
    "@id" : "https://w3id.org/con-tax#ConstructionComponent"
  } ]
}, {
  "@id" : "https://w3id.org/con-tax/properties/bhp#hasArchitecturalStyle",
  "@type" : [ "http://www.w3.org/2002/07/owl#ObjectProperty" ],
  "http://www.w3.org/2000/01/rdf-schema#comment" : [ {
    "@language" : "en",
    "@value" : "Property to indicate the architectural style of as spatial building zone or a construction component. Property definition inspired by interviews with built heritage stakeholders."
  } ],
  "http://www.w3.org/2000/01/rdf-schema#isDefinedBy" : [ {
    "@id" : "https://w3id.org/con-tax/properties/bhp"
  } ],
  "http://www.w3.org/2000/01/rdf-schema#label" : [ {
    "@language" : "en",
    "@value" : "has architectural style"
  } ],
  "http://www.w3.org/2000/01/rdf-schema#subPropertyOf" : [ {
    "@id" : "https://w3id.org/con-tax#property_OP"
  } ],
  "https://w3id.org/con-tax#domainOrSubjectIncludes" : [ {
    "@id" : "https://w3id.org/bot#Element"
  }, {
    "@id" : "https://w3id.org/bot#Zone"
  }, {
    "@id" : "https://w3id.org/con-tax#ConstructionComponent"
  } ]
}, {
  "@id" : "https://w3id.org/con-tax/properties/bhp#hasErfgoedBeheersplan",
  "@type" : [ "http://www.w3.org/2002/07/owl#ObjectProperty" ],
  "http://www.w3.org/2000/01/rdf-schema#comment" : [ {
    "@language" : "en",
    "@value" : "Property to connect a built heritage buildig or site to an \"erfgoed beheersplan\", as defined by Onroerend Erfgoed Vlaanderen. Property definition inspired by interviews with built heritage stakeholders."
  } ],
  "http://www.w3.org/2000/01/rdf-schema#isDefinedBy" : [ {
    "@id" : "https://w3id.org/con-tax/properties/bhp"
  } ],
  "http://www.w3.org/2000/01/rdf-schema#label" : [ {
    "@language" : "en",
    "@value" : "has erfgoed beheersplan"
  } ],
  "http://www.w3.org/2000/01/rdf-schema#subPropertyOf" : [ {
    "@id" : "https://w3id.org/con-tax#property_OP"
  } ],
  "https://w3id.org/con-tax#domainOrSubjectIncludes" : [ {
    "@id" : "https://w3id.org/bot#Building"
  }, {
    "@id" : "https://w3id.org/bot#Site"
  } ]
}, {
  "@id" : "https://w3id.org/con-tax/properties/bhp#heritageProtectionType",
  "@type" : [ "http://www.w3.org/2002/07/owl#ObjectProperty" ],
  "http://purl.org/dc/terms/source" : [ {
    "@id" : "https://inventaris.onroerenderfgoed.be/"
  } ],
  "http://www.w3.org/2000/01/rdf-schema#comment" : [ {
    "@language" : "en",
    "@value" : "Property to assign a heritage protection type to a certain built heritage site or building. For the Flemish context, two predefined property values can be used from the Onroerend Erfgoed thesaurus \"AANDUIDINGSTYPES\". Property definition inspired by the Onroerend Erfgoed Vlaanderen built heritage inventory."
  } ],
  "http://www.w3.org/2000/01/rdf-schema#isDefinedBy" : [ {
    "@id" : "https://w3id.org/con-tax/properties/bhp"
  } ],
  "http://www.w3.org/2000/01/rdf-schema#label" : [ {
    "@language" : "en",
    "@value" : "heritage protection type"
  } ],
  "http://www.w3.org/2000/01/rdf-schema#subPropertyOf" : [ {
    "@id" : "https://w3id.org/con-tax#property_OP"
  } ],
  "https://w3id.org/con-tax#domainOrSubjectIncludes" : [ {
    "@id" : "https://w3id.org/bot#Building"
  }, {
    "@id" : "https://w3id.org/bot#Site"
  } ],
  "https://w3id.org/con-tax#rangeOrObjectIncludes" : [ {
    "@id" : "https://id.erfgoed.net/thesauri/aanduidingstypes/1"
  }, {
    "@id" : "https://id.erfgoed.net/thesauri/aanduidingstypes/9"
  } ]
}, {
  "@id" : "https://w3id.org/con-tax/properties/bhp#heritageValue",
  "@type" : [ "http://www.w3.org/2002/07/owl#ObjectProperty" ],
  "http://purl.org/dc/terms/source" : [ {
    "@id" : "https://inventaris.onroerenderfgoed.be/"
  } ],
  "http://www.w3.org/2000/01/rdf-schema#comment" : [ {
    "@language" : "en",
    "@value" : "Property to assign a heritage value to a certain built heritage object (spatial building zone or individual construction component). For the Flemish context, predefined property values can be used from the Onroerend Erfgoed thesaurus \"WAARDETYPES\". Property definition inspired by the Onroerend Erfgoed Vlaanderen built heritage inventory."
  } ],
  "http://www.w3.org/2000/01/rdf-schema#isDefinedBy" : [ {
    "@id" : "https://w3id.org/con-tax/properties/bhp"
  } ],
  "http://www.w3.org/2000/01/rdf-schema#label" : [ {
    "@language" : "en",
    "@value" : "heritage value"
  } ],
  "http://www.w3.org/2000/01/rdf-schema#subPropertyOf" : [ {
    "@id" : "https://w3id.org/con-tax#property_OP"
  } ],
  "https://w3id.org/con-tax#domainOrSubjectIncludes" : [ {
    "@id" : "https://w3id.org/bot#Element"
  }, {
    "@id" : "https://w3id.org/bot#Zone"
  }, {
    "@id" : "https://w3id.org/con-tax#ConstructionComponent"
  } ],
  "https://w3id.org/con-tax#rangeOrObjectIncludes" : [ {
    "@id" : "https://id.erfgoed.net/thesauri/waardetypes/30"
  }, {
    "@id" : "https://id.erfgoed.net/thesauri/waardetypes/37"
  } ]
}, {
  "@id" : "https://w3id.org/con-tax/properties/bhp#locationOfHistoricalEvent",
  "@type" : [ "http://www.w3.org/2002/07/owl#ObjectProperty" ],
  "http://www.w3.org/2000/01/rdf-schema#comment" : [ {
    "@language" : "en",
    "@value" : "A property to connect a spatial building zone to a historical event that took place in the building zone. Property definition inspired by interviews with built heritage stakeholders."
  } ],
  "http://www.w3.org/2000/01/rdf-schema#isDefinedBy" : [ {
    "@id" : "https://w3id.org/con-tax/properties/bhp"
  } ],
  "http://www.w3.org/2000/01/rdf-schema#label" : [ {
    "@language" : "en",
    "@value" : "location of historical event"
  } ],
  "http://www.w3.org/2000/01/rdf-schema#subPropertyOf" : [ {
    "@id" : "https://w3id.org/con-tax#property_OP"
  } ],
  "https://w3id.org/con-tax#domainOrSubjectIncludes" : [ {
    "@id" : "https://w3id.org/bot#Zone"
  } ]
}, {
  "@id" : "https://w3id.org/con-tax/properties/bhp#mw-assessmentScore-BPC",
  "@type" : [ "http://www.w3.org/2002/07/owl#DatatypeProperty", "http://www.w3.org/2002/07/owl#FunctionalProperty" ],
  "http://purl.org/dc/terms/source" : [ {
    "@id" : "https://www.monumentenwacht.be/"
  } ],
  "http://www.w3.org/2000/01/rdf-schema#comment" : [ {
    "@language" : "en",
    "@value" : "Property to indicate the building physical condition (BPC) of an assessment (cp:Assessment) connected to an assessed object (cp:hasAssessment) according to the methodology of Monumentenwacht Vlaanderen. According to the methodology of Monumentenwacht, this type of assessment should be performed for each of the following six parts of an inspected construction: (1) the construction a whole, (2) the roof(s), (3) the rain water disposal system, (4) the roof structure(s), (5) the general load bearing structure and (6) the framework and glazing of doors and windows. \r\n\r\nThe value of the property should be a positive integer between 1 and 6. The scale should be interpretted as follows:\n1 = excellent\n2 = good\n3 = fair\n4 = average\n5 = bad\n6 = very bad"
  } ],
  "http://www.w3.org/2000/01/rdf-schema#isDefinedBy" : [ {
    "@id" : "https://w3id.org/con-tax/properties/bhp"
  } ],
  "http://www.w3.org/2000/01/rdf-schema#label" : [ {
    "@language" : "en",
    "@value" : "building physical condition score (according Monumentenwacht)"
  } ],
  "http://www.w3.org/2000/01/rdf-schema#range" : [ {
    "@id" : "http://www.w3.org/2001/XMLSchema#positiveInteger"
  } ],
  "http://www.w3.org/2000/01/rdf-schema#subPropertyOf" : [ {
    "@id" : "https://w3id.org/con-tax/properties/cp#assessmentScore"
  } ]
}, {
  "@id" : "https://w3id.org/con-tax/properties/bhp#mw-assessmentScore-RCD",
  "@type" : [ "http://www.w3.org/2002/07/owl#DatatypeProperty", "http://www.w3.org/2002/07/owl#FunctionalProperty" ],
  "http://purl.org/dc/terms/source" : [ {
    "@id" : "https://www.monumentenwacht.be/"
  } ],
  "http://www.w3.org/2000/01/rdf-schema#comment" : [ {
    "@language" : "en",
    "@value" : "Property to indicate the risk for consequential damage (in case the owner does not react properly to the detected damages) of an assessment (cp:Assessment) connected to an assessed object (cp:hasAssessment) connected to an assessed object (cp:hasAssessment) according to the methodology of Monumentenwacht Vlaanderen. According to the methodology of Monumentenwacht, this type of assessment should be performed for each of the following six parts of an inspected construction: (1) the construction a whole, (2) the roof(s), (3) the rain water disposal system, (4) the roof structure(s), (5) the general load bearing structure and (6) the framework and glazing of doors and windows. \r\n\r\nThe value of the property should be a positive integer between 1 and 6. The scale should be interpretted as follows:\n1 = no risk\n2 = low risk\n3 = fair risk\n4 = considerable risk\n5 = high risk\n6 = acute risk"
  } ],
  "http://www.w3.org/2000/01/rdf-schema#isDefinedBy" : [ {
    "@id" : "https://w3id.org/con-tax/properties/bhp"
  } ],
  "http://www.w3.org/2000/01/rdf-schema#label" : [ {
    "@language" : "en",
    "@value" : "risk for consequential damage score (according Monumentenwacht)"
  } ],
  "http://www.w3.org/2000/01/rdf-schema#range" : [ {
    "@id" : "http://www.w3.org/2001/XMLSchema#positiveInteger"
  } ],
  "http://www.w3.org/2000/01/rdf-schema#subPropertyOf" : [ {
    "@id" : "https://w3id.org/con-tax/properties/cp#assessmentScore"
  } ]
}, {
  "@id" : "https://w3id.org/con-tax/properties/bhp#mw-assessmentScore-maintenance",
  "@type" : [ "http://www.w3.org/2002/07/owl#DatatypeProperty", "http://www.w3.org/2002/07/owl#FunctionalProperty" ],
  "http://purl.org/dc/terms/source" : [ {
    "@id" : "https://www.monumentenwacht.be/"
  } ],
  "http://www.w3.org/2000/01/rdf-schema#comment" : [ {
    "@language" : "en",
    "@value" : "Property to indicate the attitude and quality of the current maintenance policies of an assessment (cp:Assessment) connected to an assessed object (cp:hasAssessment) according to the methodology of Monumentenwacht Vlaanderen. According to the methodology of Monumentenwacht, this type of assessment should be performed for each of the following six parts of an inspected construction: (1) the construction a whole, (2) the roof(s), (3) the rain water disposal system, (4) the roof structure(s), (5) the general load bearing structure and (6) the framework and glazing of doors and windows. \r\n\r\nThe value of the property should be a positive integer between 1 and 6. The scale should be interpretted as follows:\n1 = excellent\n2 = good\n3 = fair\n4 = average\n5 = bad\n6 = very bad"
  } ],
  "http://www.w3.org/2000/01/rdf-schema#isDefinedBy" : [ {
    "@id" : "https://w3id.org/con-tax/properties/bhp"
  } ],
  "http://www.w3.org/2000/01/rdf-schema#label" : [ {
    "@language" : "en",
    "@value" : "maintenance score (according Monumentenwacht)"
  } ],
  "http://www.w3.org/2000/01/rdf-schema#range" : [ {
    "@id" : "http://www.w3.org/2001/XMLSchema#positiveInteger"
  } ],
  "http://www.w3.org/2000/01/rdf-schema#subPropertyOf" : [ {
    "@id" : "https://w3id.org/con-tax/properties/cp#assessmentScore"
  } ]
}, {
  "@id" : "https://w3id.org/con-tax/properties/bhp#originalArchitect",
  "@type" : [ "http://www.w3.org/2002/07/owl#ObjectProperty" ],
  "http://purl.org/dc/terms/source" : [ {
    "@id" : "https://inventaris.onroerenderfgoed.be/"
  } ],
  "http://www.w3.org/2000/01/rdf-schema#comment" : [ {
    "@language" : "en",
    "@value" : "Property to relate an original architect to a site, building or individual construction component. Famous architects with assigned URIs from the Getty ULAN vocabulary can be used as values for this property. Property definition inspired by the Onroerend Erfgoed Vlaanderen built heritage inventory."
  } ],
  "http://www.w3.org/2000/01/rdf-schema#isDefinedBy" : [ {
    "@id" : "https://w3id.org/con-tax/properties/bhp"
  } ],
  "http://www.w3.org/2000/01/rdf-schema#label" : [ {
    "@language" : "en",
    "@value" : "original architect"
  } ],
  "http://www.w3.org/2000/01/rdf-schema#subPropertyOf" : [ {
    "@id" : "https://w3id.org/con-tax/properties/bhp#relatedArchitect"
  } ],
  "https://w3id.org/con-tax#domainOrSubjectIncludes" : [ {
    "@id" : "https://w3id.org/bot#Element"
  }, {
    "@id" : "https://w3id.org/bot#Zone"
  }, {
    "@id" : "https://w3id.org/con-tax#ConstructionComponent"
  } ]
}, {
  "@id" : "https://w3id.org/con-tax/properties/bhp#originsFromPeriod",
  "@type" : [ "http://www.w3.org/2002/07/owl#ObjectProperty" ],
  "http://www.w3.org/2000/01/rdf-schema#comment" : [ {
    "@language" : "en",
    "@value" : "Property to indicate the historical time period a spatial building zone or a construction component originates from. Property definition inspired by interviews with built heritage stakeholders."
  } ],
  "http://www.w3.org/2000/01/rdf-schema#isDefinedBy" : [ {
    "@id" : "https://w3id.org/con-tax/properties/bhp"
  } ],
  "http://www.w3.org/2000/01/rdf-schema#label" : [ {
    "@language" : "en",
    "@value" : "origins from period"
  } ],
  "http://www.w3.org/2000/01/rdf-schema#subPropertyOf" : [ {
    "@id" : "https://w3id.org/con-tax#property_OP"
  } ],
  "https://w3id.org/con-tax#domainOrSubjectIncludes" : [ {
    "@id" : "https://w3id.org/bot#Element"
  }, {
    "@id" : "https://w3id.org/bot#Zone"
  }, {
    "@id" : "https://w3id.org/con-tax#ConstructionComponent"
  } ],
  "https://w3id.org/con-tax#rangeOrObjectIncludes" : [ {
    "@id" : "https://id.erfgoed.net/thesauri/dateringen/1195"
  }, {
    "@id" : "https://id.erfgoed.net/thesauri/dateringen/1196"
  }, {
    "@id" : "https://id.erfgoed.net/thesauri/dateringen/1223"
  }, {
    "@id" : "https://id.erfgoed.net/thesauri/dateringen/1227"
  }, {
    "@id" : "https://id.erfgoed.net/thesauri/dateringen/1236"
  }, {
    "@id" : "https://id.erfgoed.net/thesauri/dateringen/1237"
  } ]
}, {
  "@id" : "https://w3id.org/con-tax/properties/bhp#percentageRoofSafetyHooks",
  "@type" : [ "http://www.w3.org/2002/07/owl#ObjectProperty" ],
  "http://purl.org/dc/terms/source" : [ {
    "@id" : "https://www.monumentenwacht.be/"
  } ],
  "http://www.w3.org/2000/01/rdf-schema#comment" : [ {
    "@language" : "en",
    "@value" : "Quantitative property to indicate the percentage of the roof that is provided with safety hooks for ladders and/or fall protection. Property definition inspired by the Monumentenwacht Vlaanderen databases (MAKSBO and IMACS)."
  } ],
  "http://www.w3.org/2000/01/rdf-schema#isDefinedBy" : [ {
    "@id" : "https://w3id.org/con-tax/properties/bhp"
  } ],
  "http://www.w3.org/2000/01/rdf-schema#label" : [ {
    "@language" : "en",
    "@value" : "% of roof safety hooks"
  } ],
  "http://www.w3.org/2000/01/rdf-schema#subPropertyOf" : [ {
    "@id" : "https://w3id.org/con-tax#property_OP"
  } ],
  "https://w3id.org/con-tax#domainOrSubjectIncludes" : [ {
    "@id" : "http://pi.pauwel.be/voc/buildingelement#Slab-ROOF"
  }, {
    "@id" : "https://w3id.org/con-tax/components/aat-arch#300002098"
  } ],
  "https://w3id.org/con-tax#rangeOrObjectIncludes" : [ {
    "@id" : "http://www.w3.org/2001/XMLSchema#decimal"
  } ]
}, {
  "@id" : "https://w3id.org/con-tax/properties/bhp#percentageRoofSafetyHooksEN517",
  "@type" : [ "http://www.w3.org/2002/07/owl#ObjectProperty" ],
  "http://purl.org/dc/terms/source" : [ {
    "@id" : "https://www.monumentenwacht.be/"
  } ],
  "http://www.w3.org/2000/01/rdf-schema#comment" : [ {
    "@language" : "en",
    "@value" : "Quantitative property to indicate the percentage of the roof that is provided with safety hooks for ladders and/or fall protection that comply with the European standard EN 517. Property definition inspired by the Monumentenwacht Vlaanderen databases (MAKSBO and IMACS)."
  } ],
  "http://www.w3.org/2000/01/rdf-schema#isDefinedBy" : [ {
    "@id" : "https://w3id.org/con-tax/properties/bhp"
  } ],
  "http://www.w3.org/2000/01/rdf-schema#label" : [ {
    "@language" : "en",
    "@value" : "% of roof safety hooks EN 517"
  } ],
  "http://www.w3.org/2000/01/rdf-schema#subPropertyOf" : [ {
    "@id" : "https://w3id.org/con-tax/properties/bhp#percentageRoofSafetyHooks"
  } ],
  "https://w3id.org/con-tax#domainOrSubjectIncludes" : [ {
    "@id" : "http://pi.pauwel.be/voc/buildingelement#Slab-ROOF"
  }, {
    "@id" : "https://w3id.org/con-tax/components/aat-arch#300002098"
  } ],
  "https://w3id.org/con-tax#rangeOrObjectIncludes" : [ {
    "@id" : "http://www.w3.org/2001/XMLSchema#decimal"
  } ]
}, {
  "@id" : "https://w3id.org/con-tax/properties/bhp#relatedArchitect",
  "@type" : [ "http://www.w3.org/2002/07/owl#ObjectProperty" ],
  "http://purl.org/dc/terms/source" : [ {
    "@id" : "https://inventaris.onroerenderfgoed.be/"
  } ],
  "http://www.w3.org/2000/01/rdf-schema#comment" : [ {
    "@language" : "en",
    "@value" : "Property to relate an architect to a site, building or individual construction component. Famous architects with assigned URIs from the Getty ULAN vocabulary can be used as values for this property. Specializations of this property can be used to assign the original architect (bhp:originalArchitect) or (recent or historic) restoration architects (bhp:restorationArchitect). Property definition inspired by the Onroerend Erfgoed Vlaanderen built heritage inventory."
  } ],
  "http://www.w3.org/2000/01/rdf-schema#isDefinedBy" : [ {
    "@id" : "https://w3id.org/con-tax/properties/bhp"
  } ],
  "http://www.w3.org/2000/01/rdf-schema#label" : [ {
    "@language" : "en",
    "@value" : "related architect"
  } ],
  "http://www.w3.org/2000/01/rdf-schema#subPropertyOf" : [ {
    "@id" : "https://w3id.org/con-tax#property_OP"
  } ],
  "https://w3id.org/con-tax#domainOrSubjectIncludes" : [ {
    "@id" : "https://w3id.org/bot#Element"
  }, {
    "@id" : "https://w3id.org/bot#Zone"
  }, {
    "@id" : "https://w3id.org/con-tax#ConstructionComponent"
  } ]
}, {
  "@id" : "https://w3id.org/con-tax/properties/bhp#restorationArchitect",
  "@type" : [ "http://www.w3.org/2002/07/owl#ObjectProperty" ],
  "http://purl.org/dc/terms/source" : [ {
    "@id" : "https://inventaris.onroerenderfgoed.be/"
  } ],
  "http://www.w3.org/2000/01/rdf-schema#comment" : [ {
    "@language" : "en",
    "@value" : "Property to relate a (recent or historic) restoration architect to a site, building or individual construction component. Famous architects with assigned URIs from the Getty ULAN vocabulary can be used as values for this property. Property definition inspired by the Onroerend Erfgoed Vlaanderen built heritage inventory."
  } ],
  "http://www.w3.org/2000/01/rdf-schema#isDefinedBy" : [ {
    "@id" : "https://w3id.org/con-tax/properties/bhp"
  } ],
  "http://www.w3.org/2000/01/rdf-schema#label" : [ {
    "@language" : "en",
    "@value" : "restoration architect"
  } ],
  "http://www.w3.org/2000/01/rdf-schema#subPropertyOf" : [ {
    "@id" : "https://w3id.org/con-tax/properties/bhp#relatedArchitect"
  } ],
  "https://w3id.org/con-tax#domainOrSubjectIncludes" : [ {
    "@id" : "https://w3id.org/bot#Element"
  }, {
    "@id" : "https://w3id.org/bot#Zone"
  }, {
    "@id" : "https://w3id.org/con-tax#ConstructionComponent"
  } ]
}, {
  "@id" : "https://w3id.org/con-tax/properties/cp#assessmentScore",
  "@type" : [ "http://www.w3.org/2002/07/owl#DatatypeProperty", "http://www.w3.org/2002/07/owl#FunctionalProperty" ]
}, {
  "@id" : "https://w3id.org/con-tax/zones/aat-buildings#300004790",
  "@type" : [ "http://www.w3.org/2002/07/owl#NamedIndividual", "http://www.w3.org/2000/01/rdf-schema#Resource" ]
}, {
  "@id" : "https://w3id.org/con-tax/zones/et-buildings#293",
  "@type" : [ "http://www.w3.org/2002/07/owl#NamedIndividual", "http://www.w3.org/2000/01/rdf-schema#Resource" ]
}, {
  "@id" : "https://w3id.org/con-tax/zones/et-buildings#319",
  "@type" : [ "http://www.w3.org/2002/07/owl#NamedIndividual", "http://www.w3.org/2000/01/rdf-schema#Resource" ]
}, {
  "@id" : "https://w3id.org/con-tax/zones/et-buildings#321",
  "@type" : [ "http://www.w3.org/2002/07/owl#NamedIndividual", "http://www.w3.org/2000/01/rdf-schema#Resource" ]
}, {
  "@id" : "https://w3id.org/con-tax/zones/et-buildings#323",
  "@type" : [ "http://www.w3.org/2002/07/owl#NamedIndividual", "http://www.w3.org/2000/01/rdf-schema#Resource" ]
}, {
  "@id" : "https://w3id.org/con-tax/zones/et-buildings#359",
  "@type" : [ "http://www.w3.org/2002/07/owl#NamedIndividual", "http://www.w3.org/2000/01/rdf-schema#Resource" ]
}, {
  "@id" : "https://w3id.org/con-tax/zones/et-buildings#466",
  "@type" : [ "http://www.w3.org/2002/07/owl#NamedIndividual", "http://www.w3.org/2000/01/rdf-schema#Resource" ]
}, {
  "@id" : "https://w3id.org/con-tax/zones/et-buildings#520",
  "@type" : [ "http://www.w3.org/2002/07/owl#NamedIndividual", "http://www.w3.org/2000/01/rdf-schema#Resource" ]
}, {
  "@id" : "https://w3id.org/con-tax/zones/et-buildings#63",
  "@type" : [ "http://www.w3.org/2002/07/owl#NamedIndividual", "http://www.w3.org/2000/01/rdf-schema#Resource" ]
}, {
  "@id" : "https://www.monumentenwacht.be/",
  "@type" : [ "http://www.w3.org/2002/07/owl#NamedIndividual", "http://www.w3.org/2000/01/rdf-schema#Resource" ]
} ]